MANIFEST.in
README.rst
setup.py
docs/HISTORY.txt
plonetheme/__init__.py
plonetheme.unilluminated.egg-info/PKG-INFO
plonetheme.unilluminated.egg-info/SOURCES.txt
plonetheme.unilluminated.egg-info/dependency_links.txt
plonetheme.unilluminated.egg-info/entry_points.txt
plonetheme.unilluminated.egg-info/namespace_packages.txt
plonetheme.unilluminated.egg-info/requires.txt
plonetheme.unilluminated.egg-info/top_level.txt
plonetheme/unilluminated/__init__.py
plonetheme/unilluminated/configure.zcml
plonetheme/unilluminated/theme/unilluminated/index.html
plonetheme/unilluminated/theme/unilluminated/rules.xml
plonetheme/unilluminated/theme/unilluminated/static/style.css
plonetheme/unilluminated/theme/unilluminated/static/images/img01.gif
plonetheme/unilluminated/theme/unilluminated/static/images/img02.gif
plonetheme/unilluminated/theme/unilluminated/static/images/img03.gif
plonetheme/unilluminated/theme/unilluminated/static/images/img05.jpg
plonetheme/unilluminated/theme/unilluminated/static/images/img06.jpg