Metadata-Version: 1.0
Name: plonetheme.unilluminated
Version: 0.1.5
Summary: An installable Diazo theme for Plone 4.1
Home-page: https://github.com/aclark4life/plonetheme.unilluminated
Author: Alex Clark
Author-email: aclark@aclark.net
License: UNKNOWN
Keywords: web zope plone theme diazo
Platform: UNKNOWN
Classifier: Framework :: Plone
Classifier: Programming Language :: Python
